Compiled from "MaidBrain.java"
public final class com.github.tartaricacid.touhoulittlemaid.entity.ai.brain.MaidBrain {
  public com.github.tartaricacid.touhoulittlemaid.entity.ai.brain.MaidBrain();
    Code:
         0: aload_0
         1: invokespecial #16                 // Method java/lang/Object."<init>":()V
         4: return

  public static com.google.common.collect.ImmutableList<net.minecraft.world.entity.ai.memory.MemoryModuleType<?>> getMemoryTypes();
    Code:
         0: bipush        12
         2: anewarray     #23                 // class net/minecraft/world/entity/ai/memory/MemoryModuleType
         5: dup
         6: iconst_0
         7: getstatic     #27                 // Field net/minecraft/world/entity/ai/memory/MemoryModuleType.PATH:Lnet/minecraft/world/entity/ai/memory/MemoryModuleType;
        10: aastore
        11: dup
        12: iconst_1
        13: getstatic     #30                 // Field net/minecraft/world/entity/ai/memory/MemoryModuleType.DOORS_TO_CLOSE:Lnet/minecraft/world/entity/ai/memory/MemoryModuleType;
        16: aastore
        17: dup
        18: iconst_2
        19: getstatic     #33                 // Field net/minecraft/world/entity/ai/memory/MemoryModuleType.LOOK_TARGET:Lnet/minecraft/world/entity/ai/memory/MemoryModuleType;
        22: aastore
        23: dup
        24: iconst_3
        25: getstatic     #36                 // Field net/minecraft/world/entity/ai/memory/MemoryModuleType.NEAREST_HOSTILE:Lnet/minecraft/world/entity/ai/memory/MemoryModuleType;
        28: aastore
        29: dup
        30: iconst_4
        31: getstatic     #39                 // Field net/minecraft/world/entity/ai/memory/MemoryModuleType.HURT_BY:Lnet/minecraft/world/entity/ai/memory/MemoryModuleType;
        34: aastore
        35: dup
        36: iconst_5
        37: getstatic     #42                 // Field net/minecraft/world/entity/ai/memory/MemoryModuleType.HURT_BY_ENTITY:Lnet/minecraft/world/entity/ai/memory/MemoryModuleType;
        40: aastore
        41: dup
        42: bipush        6
        44: getstatic     #45                 // Field net/minecraft/world/entity/ai/memory/MemoryModuleType.CANT_REACH_WALK_TARGET_SINCE:Lnet/minecraft/world/entity/ai/memory/MemoryModuleType;
        47: aastore
        48: dup
        49: bipush        7
        51: getstatic     #48                 // Field net/minecraft/world/entity/ai/memory/MemoryModuleType.WALK_TARGET:Lnet/minecraft/world/entity/ai/memory/MemoryModuleType;
        54: aastore
        55: dup
        56: bipush        8
        58: getstatic     #51                 // Field net/minecraft/world/entity/ai/memory/MemoryModuleType.ATTACK_TARGET:Lnet/minecraft/world/entity/ai/memory/MemoryModuleType;
        61: aastore
        62: dup
        63: bipush        9
        65: getstatic     #54                 // Field net/minecraft/world/entity/ai/memory/MemoryModuleType.ATTACK_COOLING_DOWN:Lnet/minecraft/world/entity/ai/memory/MemoryModuleType;
        68: aastore
        69: dup
        70: bipush        10
        72: getstatic     #60                 // Field com/github/tartaricacid/touhoulittlemaid/init/InitEntities.TARGET_POS:Ljava/util/function/Supplier;
        75: invokeinterface #66,  1           // InterfaceMethod java/util/function/Supplier.get:()Ljava/lang/Object;
        80: checkcast     #23                 // class net/minecraft/world/entity/ai/memory/MemoryModuleType
        83: aastore
        84: dup
        85: bipush        11
        87: getstatic     #69                 // Field com/github/tartaricacid/touhoulittlemaid/init/InitEntities.MAID_EDIBLE_BLOCK_ACTION:Ljava/util/function/Supplier;
        90: invokeinterface #66,  1           // InterfaceMethod java/util/function/Supplier.get:()Ljava/lang/Object;
        95: checkcast     #23                 // class net/minecraft/world/entity/ai/memory/MemoryModuleType
        98: aastore
        99: invokestatic  #75                 // Method com/google/common/collect/Lists.newArrayList:([Ljava/lang/Object;)Ljava/util/ArrayList;
       102: astore_0
       103: getstatic     #81                 // Field com/github/tartaricacid/touhoulittlemaid/entity/ai/brain/ExtraMaidBrainManager.EXTRA_MAID_BRAINS:Ljava/util/List;
       106: aload_0
       107: invokedynamic #101,  0            // InvokeDynamic #0:accept:(Ljava/util/List;)Ljava/util/function/Consumer;
       112: invokeinterface #107,  2          // InterfaceMethod java/util/List.forEach:(Ljava/util/function/Consumer;)V
       117: aload_0
       118: invokestatic  #113                // Method com/google/common/collect/ImmutableList.copyOf:(Ljava/util/Collection;)Lcom/google/common/collect/ImmutableList;
       121: areturn

  public static com.google.common.collect.ImmutableList<net.minecraft.world.entity.ai.sensing.SensorType<? extends net.minecraft.world.entity.ai.sensing.Sensor<? super com.github.tartaricacid.touhoulittlemaid.entity.passive.EntityMaid>>> getSensorTypes();
    Code:
         0: iconst_4
         1: anewarray     #119                // class net/minecraft/world/entity/ai/sensing/SensorType
         4: dup
         5: iconst_0
         6: getstatic     #122                // Field com/github/tartaricacid/touhoulittlemaid/init/InitEntities.MAID_NEAREST_LIVING_ENTITY_SENSOR:Ljava/util/function/Supplier;
         9: invokeinterface #66,  1           // InterfaceMethod java/util/function/Supplier.get:()Ljava/lang/Object;
        14: checkcast     #119                // class net/minecraft/world/entity/ai/sensing/SensorType
        17: aastore
        18: dup
        19: iconst_1
        20: getstatic     #125                // Field net/minecraft/world/entity/ai/sensing/SensorType.HURT_BY:Lnet/minecraft/world/entity/ai/sensing/SensorType;
        23: aastore
        24: dup
        25: iconst_2
        26: getstatic     #128                // Field com/github/tartaricacid/touhoulittlemaid/init/InitEntities.MAID_HOSTILES_SENSOR:Ljava/util/function/Supplier;
        29: invokeinterface #66,  1           // InterfaceMethod java/util/function/Supplier.get:()Ljava/lang/Object;
        34: checkcast     #119                // class net/minecraft/world/entity/ai/sensing/SensorType
        37: aastore
        38: dup
        39: iconst_3
        40: getstatic     #131                // Field com/github/tartaricacid/touhoulittlemaid/init/InitEntities.MAID_PICKUP_ENTITIES_SENSOR:Ljava/util/function/Supplier;
        43: invokeinterface #66,  1           // InterfaceMethod java/util/function/Supplier.get:()Ljava/lang/Object;
        48: checkcast     #119                // class net/minecraft/world/entity/ai/sensing/SensorType
        51: aastore
        52: invokestatic  #75                 // Method com/google/common/collect/Lists.newArrayList:([Ljava/lang/Object;)Ljava/util/ArrayList;
        55: astore_0
        56: getstatic     #81                 // Field com/github/tartaricacid/touhoulittlemaid/entity/ai/brain/ExtraMaidBrainManager.EXTRA_MAID_BRAINS:Ljava/util/List;
        59: aload_0
        60: invokedynamic #136,  0            // InvokeDynamic #1:accept:(Ljava/util/List;)Ljava/util/function/Consumer;
        65: invokeinterface #107,  2          // InterfaceMethod java/util/List.forEach:(Ljava/util/function/Consumer;)V
        70: aload_0
        71: invokestatic  #113                // Method com/google/common/collect/ImmutableList.copyOf:(Ljava/util/Collection;)Lcom/google/common/collect/ImmutableList;
        74: areturn

  public static void registerBrainGoals(net.minecraft.world.entity.ai.Brain<com.github.tartaricacid.touhoulittlemaid.entity.passive.EntityMaid>, com.github.tartaricacid.touhoulittlemaid.entity.passive.EntityMaid);
    Code:
         0: aload_0
         1: aload_1
         2: invokestatic  #143                // Method registerSchedule:(Lnet/minecraft/world/entity/ai/Brain;Lcom/github/tartaricacid/touhoulittlemaid/entity/passive/EntityMaid;)V
         5: aload_0
         6: invokestatic  #147                // Method registerCoreGoals:(Lnet/minecraft/world/entity/ai/Brain;)V
         9: aload_0
        10: invokestatic  #150                // Method registerPanicGoals:(Lnet/minecraft/world/entity/ai/Brain;)V
        13: aload_0
        14: invokestatic  #153                // Method registerRideIdleGoals:(Lnet/minecraft/world/entity/ai/Brain;)V
        17: aload_0
        18: aload_1
        19: invokestatic  #156                // Method registerRideWorkGoals:(Lnet/minecraft/world/entity/ai/Brain;Lcom/github/tartaricacid/touhoulittlemaid/entity/passive/EntityMaid;)V
        22: aload_0
        23: invokestatic  #159                // Method registerRideRestGoals:(Lnet/minecraft/world/entity/ai/Brain;)V
        26: aload_0
        27: invokestatic  #162                // Method registerIdleGoals:(Lnet/minecraft/world/entity/ai/Brain;)V
        30: aload_0
        31: aload_1
        32: invokestatic  #165                // Method registerWorkGoals:(Lnet/minecraft/world/entity/ai/Brain;Lcom/github/tartaricacid/touhoulittlemaid/entity/passive/EntityMaid;)V
        35: aload_0
        36: invokestatic  #168                // Method registerRestGoals:(Lnet/minecraft/world/entity/ai/Brain;)V
        39: aload_0
        40: getstatic     #174                // Field net/minecraft/world/entity/schedule/Activity.CORE:Lnet/minecraft/world/entity/schedule/Activity;
        43: invokestatic  #180                // Method com/google/common/collect/ImmutableSet.of:(Ljava/lang/Object;)Lcom/google/common/collect/ImmutableSet;
        46: invokevirtual #186                // Method net/minecraft/world/entity/ai/Brain.setCoreActivities:(Ljava/util/Set;)V
        49: aload_0
        50: getstatic     #189                // Field net/minecraft/world/entity/schedule/Activity.IDLE:Lnet/minecraft/world/entity/schedule/Activity;
        53: invokevirtual #193                // Method net/minecraft/world/entity/ai/Brain.setDefaultActivity:(Lnet/minecraft/world/entity/schedule/Activity;)V
        56: aload_0
        57: getstatic     #189                // Field net/minecraft/world/entity/schedule/Activity.IDLE:Lnet/minecraft/world/entity/schedule/Activity;
        60: invokevirtual #196                // Method net/minecraft/world/entity/ai/Brain.setActiveActivityIfPossible:(Lnet/minecraft/world/entity/schedule/Activity;)V
        63: aload_1
        64: aload_0
        65: invokestatic  #202                // Method com/github/tartaricacid/touhoulittlemaid/entity/ai/brain/task/MaidUpdateActivityFromSchedule.updateActivityFromSchedule:(Lcom/github/tartaricacid/touhoulittlemaid/entity/passive/EntityMaid;Lnet/minecraft/world/entity/ai/Brain;)V
        68: return

  private static void registerSchedule(net.minecraft.world.entity.ai.Brain<com.github.tartaricacid.touhoulittlemaid.entity.passive.EntityMaid>, com.github.tartaricacid.touhoulittlemaid.entity.passive.EntityMaid);
    Code:
         0: getstatic     #211                // Field com/github/tartaricacid/touhoulittlemaid/entity/ai/brain/MaidBrain$1.$SwitchMap$com$github$tartaricacid$touhoulittlemaid$entity$ai$brain$MaidSchedule:[I
         3: aload_1
         4: invokevirtual #217                // Method com/github/tartaricacid/touhoulittlemaid/entity/passive/EntityMaid.getSchedule:()Lcom/github/tartaricacid/touhoulittlemaid/entity/ai/brain/MaidSchedule;
         7: invokevirtual #223                // Method com/github/tartaricacid/touhoulittlemaid/entity/ai/brain/MaidSchedule.ordinal:()I
        10: iaload
        11: tableswitch   { // 1 to 3

                       1: 36

                       2: 54

                       3: 72
                 default: 72
            }
        36: aload_0
        37: getstatic     #226                // Field com/github/tartaricacid/touhoulittlemaid/init/InitEntities.MAID_ALL_DAY_SCHEDULES:Ljava/util/function/Supplier;
        40: invokeinterface #66,  1           // InterfaceMethod java/util/function/Supplier.get:()Ljava/lang/Object;
        45: checkcast     #228                // class net/minecraft/world/entity/schedule/Schedule
        48: invokevirtual #232                // Method net/minecraft/world/entity/ai/Brain.setSchedule:(Lnet/minecraft/world/entity/schedule/Schedule;)V
        51: goto          87
        54: aload_0
        55: getstatic     #235                // Field com/github/tartaricacid/touhoulittlemaid/init/InitEntities.MAID_NIGHT_SHIFT_SCHEDULES:Ljava/util/function/Supplier;
        58: invokeinterface #66,  1           // InterfaceMethod java/util/function/Supplier.get:()Ljava/lang/Object;
        63: checkcast     #228                // class net/minecraft/world/entity/schedule/Schedule
        66: invokevirtual #232                // Method net/minecraft/world/entity/ai/Brain.setSchedule:(Lnet/minecraft/world/entity/schedule/Schedule;)V
        69: goto          87
        72: aload_0
        73: getstatic     #238                // Field com/github/tartaricacid/touhoulittlemaid/init/InitEntities.MAID_DAY_SHIFT_SCHEDULES:Ljava/util/function/Supplier;
        76: invokeinterface #66,  1           // InterfaceMethod java/util/function/Supplier.get:()Ljava/lang/Object;
        81: checkcast     #228                // class net/minecraft/world/entity/schedule/Schedule
        84: invokevirtual #232                // Method net/minecraft/world/entity/ai/Brain.setSchedule:(Lnet/minecraft/world/entity/schedule/Schedule;)V
        87: return

  private static void registerCoreGoals(net.minecraft.world.entity.ai.Brain<com.github.tartaricacid.touhoulittlemaid.entity.passive.EntityMaid>);
    Code:
         0: iconst_0
         1: invokestatic  #245                // Method java/lang/Integer.valueOf:(I)Ljava/lang/Integer;
         4: new           #247                // class com/github/tartaricacid/touhoulittlemaid/entity/ai/brain/task/MaidSwimJumpTask
         7: dup
         8: ldc           #248                // float 0.8f
        10: invokespecial #251                // Method com/github/tartaricacid/touhoulittlemaid/entity/ai/brain/task/MaidSwimJumpTask."<init>":(F)V
        13: invokestatic  #256                // Method com/mojang/datafixers/util/Pair.of:(Ljava/lang/Object;Ljava/lang/Object;)Lcom/mojang/datafixers/util/Pair;
        16: astore_1
        17: iconst_0
        18: invokestatic  #245                // Method java/lang/Integer.valueOf:(I)Ljava/lang/Integer;
        21: new           #258                // class com/github/tartaricacid/touhoulittlemaid/entity/ai/brain/task/MaidBreathAirTask
        24: dup
        25: invokespecial #259                // Method com/github/tartaricacid/touhoulittlemaid/entity/ai/brain/task/MaidBreathAirTask."<init>":()V
        28: invokestatic  #256                // Method com/mojang/datafixers/util/Pair.of:(Ljava/lang/Object;Ljava/lang/Object;)Lcom/mojang/datafixers/util/Pair;
        31: astore_2
        32: iconst_0
        33: invokestatic  #245                // Method java/lang/Integer.valueOf:(I)Ljava/lang/Integer;
        36: new           #261                // class com/github/tartaricacid/touhoulittlemaid/entity/ai/brain/task/MaidBreathAirStopTask
        39: dup
        40: invokespecial #262                // Method com/github/tartaricacid/touhoulittlemaid/entity/ai/brain/task/MaidBreathAirStopTask."<init>":()V
        43: invokestatic  #256                // Method com/mojang/datafixers/util/Pair.of:(Ljava/lang/Object;Ljava/lang/Object;)Lcom/mojang/datafixers/util/Pair;
        46: astore_3
        47: iconst_0
        48: invokestatic  #245                // Method java/lang/Integer.valueOf:(I)Ljava/lang/Integer;
        51: new           #264                // class com/github/tartaricacid/touhoulittlemaid/entity/ai/brain/task/MaidClimbTask
        54: dup
        55: invokespecial #265                // Method com/github/tartaricacid/touhoulittlemaid/entity/ai/brain/task/MaidClimbTask."<init>":()V
        58: invokestatic  #256                // Method com/mojang/datafixers/util/Pair.of:(Ljava/lang/Object;Ljava/lang/Object;)Lcom/mojang/datafixers/util/Pair;
        61: astore        4
        63: iconst_0
        64: invokestatic  #245                // Method java/lang/Integer.valueOf:(I)Ljava/lang/Integer;
        67: new           #267                // class net/minecraft/world/entity/ai/behavior/LookAtTargetSink
        70: dup
        71: bipush        45
        73: bipush        90
        75: invokespecial #270                // Method net/minecraft/world/entity/ai/behavior/LookAtTargetSink."<init>":(II)V
        78: invokestatic  #256                // Method com/mojang/datafixers/util/Pair.of:(Ljava/lang/Object;Ljava/lang/Object;)Lcom/mojang/datafixers/util/Pair;
        81: astore        5
        83: iconst_1
        84: invokestatic  #245                // Method java/lang/Integer.valueOf:(I)Ljava/lang/Integer;
        87: new           #272                // class com/github/tartaricacid/touhoulittlemaid/entity/ai/brain/task/MaidPanicTask
        90: dup
        91: invokespecial #273                // Method com/github/tartaricacid/touhoulittlemaid/entity/ai/brain/task/MaidPanicTask."<init>":()V
        94: invokestatic  #256                // Method com/mojang/datafixers/util/Pair.of:(Ljava/lang/Object;Ljava/lang/Object;)Lcom/mojang/datafixers/util/Pair;
        97: astore        6
        99: iconst_1
       100: invokestatic  #245                // Method java/lang/Integer.valueOf:(I)Ljava/lang/Integer;
       103: new           #275                // class com/github/tartaricacid/touhoulittlemaid/entity/ai/brain/task/MaidAwaitTask
       106: dup
       107: invokespecial #276                // Method com/github/tartaricacid/touhoulittlemaid/entity/ai/brain/task/MaidAwaitTask."<init>":()V
       110: invokestatic  #256                // Method com/mojang/datafixers/util/Pair.of:(Ljava/lang/Object;Ljava/lang/Object;)Lcom/mojang/datafixers/util/Pair;
       113: astore        7
       115: iconst_2
       116: invokestatic  #245                // Method java/lang/Integer.valueOf:(I)Ljava/lang/Integer;
       119: invokestatic  #282                // Method com/github/tartaricacid/touhoulittlemaid/entity/ai/brain/task/MaidInteractWithDoor.create:()Lnet/minecraft/world/entity/ai/behavior/BehaviorControl;
       122: invokestatic  #256                // Method com/mojang/datafixers/util/Pair.of:(Ljava/lang/Object;Ljava/lang/Object;)Lcom/mojang/datafixers/util/Pair;
       125: astore        8
       127: iconst_2
       128: invokestatic  #245                // Method java/lang/Integer.valueOf:(I)Ljava/lang/Integer;
       131: new           #284                // class net/minecraft/world/entity/ai/behavior/MoveToTargetSink
       134: dup
       135: invokespecial #285                // Method net/minecraft/world/entity/ai/behavior/MoveToTargetSink."<init>":()V
       138: invokestatic  #256                // Method com/mojang/datafixers/util/Pair.of:(Ljava/lang/Object;Ljava/lang/Object;)Lcom/mojang/datafixers/util/Pair;
       141: astore        9
       143: iconst_3
       144: invokestatic  #245                // Method java/lang/Integer.valueOf:(I)Ljava/lang/Integer;
       147: new           #287                // class com/github/tartaricacid/touhoulittlemaid/entity/ai/brain/task/MaidFollowOwnerTask
       150: dup
       151: ldc_w         #288                // float 0.5f
       154: iconst_2
       155: invokespecial #291                // Method com/github/tartaricacid/touhoulittlemaid/entity/ai/brain/task/MaidFollowOwnerTask."<init>":(FI)V
       158: invokestatic  #256                // Method com/mojang/datafixers/util/Pair.of:(Ljava/lang/Object;Ljava/lang/Object;)Lcom/mojang/datafixers/util/Pair;
       161: astore        10
       163: iconst_3
       164: invokestatic  #245                // Method java/lang/Integer.valueOf:(I)Ljava/lang/Integer;
       167: new           #293                // class com/github/tartaricacid/touhoulittlemaid/entity/ai/brain/task/MaidFollowOwnerVehicleTask
       170: dup
       171: ldc_w         #288                // float 0.5f
       174: iconst_2
       175: invokespecial #294                // Method com/github/tartaricacid/touhoulittlemaid/entity/ai/brain/task/MaidFollowOwnerVehicleTask."<init>":(FI)V
       178: invokestatic  #256                // Method com/mojang/datafixers/util/Pair.of:(Ljava/lang/Object;Ljava/lang/Object;)Lcom/mojang/datafixers/util/Pair;
       181: astore        11
       183: iconst_3
       184: invokestatic  #245                // Method java/lang/Integer.valueOf:(I)Ljava/lang/Integer;
       187: new           #296                // class com/github/tartaricacid/touhoulittlemaid/entity/ai/brain/task/MaidHealSelfTask
       190: dup
       191: invokespecial #297                // Method com/github/tartaricacid/touhoulittlemaid/entity/ai/brain/task/MaidHealSelfTask."<init>":()V
       194: invokestatic  #256                // Method com/mojang/datafixers/util/Pair.of:(Ljava/lang/Object;Ljava/lang/Object;)Lcom/mojang/datafixers/util/Pair;
       197: astore        12
       199: bipush        10
       201: invokestatic  #245                // Method java/lang/Integer.valueOf:(I)Ljava/lang/Integer;
       204: new           #299                // class com/github/tartaricacid/touhoulittlemaid/entity/ai/brain/task/MaidPickupEntitiesTask
       207: dup
       208: invokedynamic #312,  0            // InvokeDynamic #2:test:()Ljava/util/function/Predicate;
       213: ldc_w         #313                // float 0.6f
       216: invokespecial #316                // Method com/github/tartaricacid/touhoulittlemaid/entity/ai/brain/task/MaidPickupEntitiesTask."<init>":(Ljava/util/function/Predicate;F)V
       219: invokestatic  #256                // Method com/mojang/datafixers/util/Pair.of:(Ljava/lang/Object;Ljava/lang/Object;)Lcom/mojang/datafixers/util/Pair;
       222: astore        13
       224: bipush        99
       226: invokestatic  #245                // Method java/lang/Integer.valueOf:(I)Ljava/lang/Integer;
       229: new           #318                // class com/github/tartaricacid/touhoulittlemaid/entity/ai/brain/task/MaidClearSleepTask
       232: dup
       233: invokespecial #319                // Method com/github/tartaricacid/touhoulittlemaid/entity/ai/brain/task/MaidClearSleepTask."<init>":()V
       236: invokestatic  #256                // Method com/mojang/datafixers/util/Pair.of:(Ljava/lang/Object;Ljava/lang/Object;)Lcom/mojang/datafixers/util/Pair;
       239: astore        14
       241: bipush        14
       243: anewarray     #253                // class com/mojang/datafixers/util/Pair
       246: dup
       247: iconst_0
       248: aload_1
       249: aastore
       250: dup
       251: iconst_1
       252: aload         4
       254: aastore
       255: dup
       256: iconst_2
       257: aload_2
       258: aastore
       259: dup
       260: iconst_3
       261: aload_3
       262: aastore
       263: dup
       264: iconst_4
       265: aload         5
       267: aastore
       268: dup
       269: iconst_5
       270: aload         6
       272: aastore
       273: dup
       274: bipush        6
       276: aload         7
       278: aastore
       279: dup
       280: bipush        7
       282: aload         8
       284: aastore
       285: dup
       286: bipush        8
       288: aload         9
       290: aastore
       291: dup
       292: bipush        9
       294: aload         10
       296: aastore
       297: dup
       298: bipush        10
       300: aload         11
       302: aastore
       303: dup
       304: bipush        11
       306: aload         12
       308: aastore
       309: dup
       310: bipush        12
       312: aload         13
       314: aastore
       315: dup
       316: bipush        13
       318: aload         14
       320: aastore
       321: invokestatic  #75                 // Method com/google/common/collect/Lists.newArrayList:([Ljava/lang/Object;)Ljava/util/ArrayList;
       324: astore        15
       326: getstatic     #81                 // Field com/github/tartaricacid/touhoulittlemaid/entity/ai/brain/ExtraMaidBrainManager.EXTRA_MAID_BRAINS:Ljava/util/List;
       329: aload         15
       331: invokedynamic #324,  0            // InvokeDynamic #3:accept:(Ljava/util/List;)Ljava/util/function/Consumer;
       336: invokeinterface #107,  2          // InterfaceMethod java/util/List.forEach:(Ljava/util/function/Consumer;)V
       341: aload_0
       342: getstatic     #174                // Field net/minecraft/world/entity/schedule/Activity.CORE:Lnet/minecraft/world/entity/schedule/Activity;
       345: aload         15
       347: invokestatic  #113                // Method com/google/common/collect/ImmutableList.copyOf:(Ljava/util/Collection;)Lcom/google/common/collect/ImmutableList;
       350: invokevirtual #328                // Method net/minecraft/world/entity/ai/Brain.addActivity:(Lnet/minecraft/world/entity/schedule/Activity;Lcom/google/common/collect/ImmutableList;)V
       353: return

  private static void registerIdleGoals(net.minecraft.world.entity.ai.Brain<com.github.tartaricacid.touhoulittlemaid.entity.passive.EntityMaid>);
    Code:
         0: iconst_5
         1: invokestatic  #245                // Method java/lang/Integer.valueOf:(I)Ljava/lang/Integer;
         4: new           #348                // class com/github/tartaricacid/touhoulittlemaid/entity/ai/brain/task/MaidBegTask
         7: dup
         8: invokespecial #349                // Method com/github/tartaricacid/touhoulittlemaid/entity/ai/brain/task/MaidBegTask."<init>":()V
        11: invokestatic  #256                // Method com/mojang/datafixers/util/Pair.of:(Ljava/lang/Object;Ljava/lang/Object;)Lcom/mojang/datafixers/util/Pair;
        14: astore_1
        15: bipush        6
        17: invokestatic  #245                // Method java/lang/Integer.valueOf:(I)Ljava/lang/Integer;
        20: new           #351                // class com/github/tartaricacid/touhoulittlemaid/entity/ai/brain/task/MaidFindHomeMealTask
        23: dup
        24: ldc_w         #313                // float 0.6f
        27: iconst_2
        28: invokespecial #352                // Method com/github/tartaricacid/touhoulittlemaid/entity/ai/brain/task/MaidFindHomeMealTask."<init>":(FI)V
        31: invokestatic  #256                // Method com/mojang/datafixers/util/Pair.of:(Ljava/lang/Object;Ljava/lang/Object;)Lcom/mojang/datafixers/util/Pair;
        34: astore_2
        35: bipush        7
        37: invokestatic  #245                // Method java/lang/Integer.valueOf:(I)Ljava/lang/Integer;
        40: new           #354                // class com/github/tartaricacid/touhoulittlemaid/entity/ai/brain/task/MaidJoyTask
        43: dup
        44: ldc_w         #313                // float 0.6f
        47: iconst_2
        48: invokespecial #355                // Method com/github/tartaricacid/touhoulittlemaid/entity/ai/brain/task/MaidJoyTask."<init>":(FI)V
        51: invokestatic  #256                // Method com/mojang/datafixers/util/Pair.of:(Ljava/lang/Object;Ljava/lang/Object;)Lcom/mojang/datafixers/util/Pair;
        54: astore_3
        55: bipush        8
        57: invokestatic  #245                // Method java/lang/Integer.valueOf:(I)Ljava/lang/Integer;
        60: new           #357                // class com/github/tartaricacid/touhoulittlemaid/entity/ai/brain/task/MaidStealEdibleMoveBlockTask
        63: dup
        64: ldc_w         #313                // float 0.6f
        67: invokespecial #358                // Method com/github/tartaricacid/touhoulittlemaid/entity/ai/brain/task/MaidStealEdibleMoveBlockTask."<init>":(F)V
        70: invokestatic  #256                // Method com/mojang/datafixers/util/Pair.of:(Ljava/lang/Object;Ljava/lang/Object;)Lcom/mojang/datafixers/util/Pair;
        73: astore        4
        75: bipush        8
        77: invokestatic  #245                // Method java/lang/Integer.valueOf:(I)Ljava/lang/Integer;
        80: new           #360                // class com/github/tartaricacid/touhoulittlemaid/entity/ai/brain/task/MaidStealEdibleUseTask
        83: dup
        84: ldc2_w        #361                // double 2.0d
        87: invokespecial #365                // Method com/github/tartaricacid/touhoulittlemaid/entity/ai/brain/task/MaidStealEdibleUseTask."<init>":(D)V
        90: invokestatic  #256                // Method com/mojang/datafixers/util/Pair.of:(Ljava/lang/Object;Ljava/lang/Object;)Lcom/mojang/datafixers/util/Pair;
        93: astore        5
        95: bipush        20
        97: invokestatic  #245                // Method java/lang/Integer.valueOf:(I)Ljava/lang/Integer;
       100: invokedynamic #370,  0            // InvokeDynamic #4:test:()Ljava/util/function/Predicate;
       105: invokestatic  #374                // Method getLookAndRandomWalk:(Ljava/util/function/Predicate;)Lcom/github/tartaricacid/touhoulittlemaid/entity/ai/brain/task/MaidRunOne;
       108: invokestatic  #256                // Method com/mojang/datafixers/util/Pair.of:(Ljava/lang/Object;Ljava/lang/Object;)Lcom/mojang/datafixers/util/Pair;
       111: astore        6
       113: bipush        99
       115: invokestatic  #245                // Method java/lang/Integer.valueOf:(I)Ljava/lang/Integer;
       118: new           #198                // class com/github/tartaricacid/touhoulittlemaid/entity/ai/brain/task/MaidUpdateActivityFromSchedule
       121: dup
       122: invokespecial #375                // Method com/github/tartaricacid/touhoulittlemaid/entity/ai/brain/task/MaidUpdateActivityFromSchedule."<init>":()V
       125: invokestatic  #256                // Method com/mojang/datafixers/util/Pair.of:(Ljava/lang/Object;Ljava/lang/Object;)Lcom/mojang/datafixers/util/Pair;
       128: astore        7
       130: bipush        7
       132: anewarray     #253                // class com/mojang/datafixers/util/Pair
       135: dup
       136: iconst_0
       137: aload_1
       138: aastore
       139: dup
       140: iconst_1
       141: aload_2
       142: aastore
       143: dup
       144: iconst_2
       145: aload_3
       146: aastore
       147: dup
       148: iconst_3
       149: aload         4
       151: aastore
       152: dup
       153: iconst_4
       154: aload         5
       156: aastore
       157: dup
       158: iconst_5
       159: aload         6
       161: aastore
       162: dup
       163: bipush        6
       165: aload         7
       167: aastore
       168: invokestatic  #75                 // Method com/google/common/collect/Lists.newArrayList:([Ljava/lang/Object;)Ljava/util/ArrayList;
       171: astore        8
       173: getstatic     #81                 // Field com/github/tartaricacid/touhoulittlemaid/entity/ai/brain/ExtraMaidBrainManager.EXTRA_MAID_BRAINS:Ljava/util/List;
       176: aload         8
       178: invokedynamic #380,  0            // InvokeDynamic #5:accept:(Ljava/util/List;)Ljava/util/function/Consumer;
       183: invokeinterface #107,  2          // InterfaceMethod java/util/List.forEach:(Ljava/util/function/Consumer;)V
       188: aload_0
       189: getstatic     #189                // Field net/minecraft/world/entity/schedule/Activity.IDLE:Lnet/minecraft/world/entity/schedule/Activity;
       192: aload         8
       194: invokestatic  #113                // Method com/google/common/collect/ImmutableList.copyOf:(Ljava/util/Collection;)Lcom/google/common/collect/ImmutableList;
       197: invokevirtual #328                // Method net/minecraft/world/entity/ai/Brain.addActivity:(Lnet/minecraft/world/entity/schedule/Activity;Lcom/google/common/collect/ImmutableList;)V
       200: return

  private static void registerWorkGoals(net.minecraft.world.entity.ai.Brain<com.github.tartaricacid.touhoulittlemaid.entity.passive.EntityMaid>, com.github.tartaricacid.touhoulittlemaid.entity.passive.EntityMaid);
    Code:
         0: bipush        99
         2: invokestatic  #245                // Method java/lang/Integer.valueOf:(I)Ljava/lang/Integer;
         5: new           #198                // class com/github/tartaricacid/touhoulittlemaid/entity/ai/brain/task/MaidUpdateActivityFromSchedule
         8: dup
         9: invokespecial #375                // Method com/github/tartaricacid/touhoulittlemaid/entity/ai/brain/task/MaidUpdateActivityFromSchedule."<init>":()V
        12: invokestatic  #256                // Method com/mojang/datafixers/util/Pair.of:(Ljava/lang/Object;Ljava/lang/Object;)Lcom/mojang/datafixers/util/Pair;
        15: astore_2
        16: aload_1
        17: invokevirtual #391                // Method com/github/tartaricacid/touhoulittlemaid/entity/passive/EntityMaid.getTask:()Lcom/github/tartaricacid/touhoulittlemaid/api/task/IMaidTask;
        20: astore_3
        21: aload_3
        22: aload_1
        23: invokeinterface #397,  2          // InterfaceMethod com/github/tartaricacid/touhoulittlemaid/api/task/IMaidTask.createBrainTasks:(Lcom/github/tartaricacid/touhoulittlemaid/entity/passive/EntityMaid;)Ljava/util/List;
        28: astore        4
        30: aload         4
        32: invokeinterface #400,  1          // InterfaceMethod java/util/List.isEmpty:()Z
        37: ifeq          56
        40: iconst_1
        41: anewarray     #253                // class com/mojang/datafixers/util/Pair
        44: dup
        45: iconst_0
        46: aload_2
        47: aastore
        48: invokestatic  #75                 // Method com/google/common/collect/Lists.newArrayList:([Ljava/lang/Object;)Ljava/util/ArrayList;
        51: astore        4
        53: goto          65
        56: aload         4
        58: aload_2
        59: invokeinterface #403,  2          // InterfaceMethod java/util/List.add:(Ljava/lang/Object;)Z
        64: pop
        65: aload         4
        67: bipush        6
        69: invokestatic  #245                // Method java/lang/Integer.valueOf:(I)Ljava/lang/Integer;
        72: new           #348                // class com/github/tartaricacid/touhoulittlemaid/entity/ai/brain/task/MaidBegTask
        75: dup
        76: invokespecial #349                // Method com/github/tartaricacid/touhoulittlemaid/entity/ai/brain/task/MaidBegTask."<init>":()V
        79: invokestatic  #256                // Method com/mojang/datafixers/util/Pair.of:(Ljava/lang/Object;Ljava/lang/Object;)Lcom/mojang/datafixers/util/Pair;
        82: invokeinterface #403,  2          // InterfaceMethod java/util/List.add:(Ljava/lang/Object;)Z
        87: pop
        88: aload         4
        90: bipush        7
        92: invokestatic  #245                // Method java/lang/Integer.valueOf:(I)Ljava/lang/Integer;
        95: new           #405                // class com/github/tartaricacid/touhoulittlemaid/entity/ai/brain/task/MaidWorkMealTask
        98: dup
        99: invokespecial #406                // Method com/github/tartaricacid/touhoulittlemaid/entity/ai/brain/task/MaidWorkMealTask."<init>":()V
       102: invokestatic  #256                // Method com/mojang/datafixers/util/Pair.of:(Ljava/lang/Object;Ljava/lang/Object;)Lcom/mojang/datafixers/util/Pair;
       105: invokeinterface #403,  2          // InterfaceMethod java/util/List.add:(Ljava/lang/Object;)Z
       110: pop
       111: aload         4
       113: bipush        8
       115: invokestatic  #245                // Method java/lang/Integer.valueOf:(I)Ljava/lang/Integer;
       118: new           #357                // class com/github/tartaricacid/touhoulittlemaid/entity/ai/brain/task/MaidStealEdibleMoveBlockTask
       121: dup
       122: ldc_w         #313                // float 0.6f
       125: invokespecial #358                // Method com/github/tartaricacid/touhoulittlemaid/entity/ai/brain/task/MaidStealEdibleMoveBlockTask."<init>":(F)V
       128: invokestatic  #256                // Method com/mojang/datafixers/util/Pair.of:(Ljava/lang/Object;Ljava/lang/Object;)Lcom/mojang/datafixers/util/Pair;
       131: invokeinterface #403,  2          // InterfaceMethod java/util/List.add:(Ljava/lang/Object;)Z
       136: pop
       137: aload         4
       139: bipush        8
       141: invokestatic  #245                // Method java/lang/Integer.valueOf:(I)Ljava/lang/Integer;
       144: new           #360                // class com/github/tartaricacid/touhoulittlemaid/entity/ai/brain/task/MaidStealEdibleUseTask
       147: dup
       148: ldc2_w        #361                // double 2.0d
       151: invokespecial #365                // Method com/github/tartaricacid/touhoulittlemaid/entity/ai/brain/task/MaidStealEdibleUseTask."<init>":(D)V
       154: invokestatic  #256                // Method com/mojang/datafixers/util/Pair.of:(Ljava/lang/Object;Ljava/lang/Object;)Lcom/mojang/datafixers/util/Pair;
       157: invokeinterface #403,  2          // InterfaceMethod java/util/List.add:(Ljava/lang/Object;)Z
       162: pop
       163: aload         4
       165: bipush        20
       167: invokestatic  #245                // Method java/lang/Integer.valueOf:(I)Ljava/lang/Integer;
       170: invokedynamic #411,  0            // InvokeDynamic #6:test:()Ljava/util/function/Predicate;
       175: invokestatic  #374                // Method getLookAndRandomWalk:(Ljava/util/function/Predicate;)Lcom/github/tartaricacid/touhoulittlemaid/entity/ai/brain/task/MaidRunOne;
       178: invokestatic  #256                // Method com/mojang/datafixers/util/Pair.of:(Ljava/lang/Object;Ljava/lang/Object;)Lcom/mojang/datafixers/util/Pair;
       181: invokeinterface #403,  2          // InterfaceMethod java/util/List.add:(Ljava/lang/Object;)Z
       186: pop
       187: getstatic     #81                 // Field com/github/tartaricacid/touhoulittlemaid/entity/ai/brain/ExtraMaidBrainManager.EXTRA_MAID_BRAINS:Ljava/util/List;
       190: invokeinterface #415,  1          // InterfaceMethod java/util/List.iterator:()Ljava/util/Iterator;
       195: astore        5
       197: aload         5
       199: invokeinterface #420,  1          // InterfaceMethod java/util/Iterator.hasNext:()Z
       204: ifeq          237
       207: aload         5
       209: invokeinterface #423,  1          // InterfaceMethod java/util/Iterator.next:()Ljava/lang/Object;
       214: checkcast     #425                // class com/github/tartaricacid/touhoulittlemaid/api/entity/ai/IExtraMaidBrain
       217: astore        6
       219: aload         4
       221: aload         6
       223: invokeinterface #429,  1          // InterfaceMethod com/github/tartaricacid/touhoulittlemaid/api/entity/ai/IExtraMaidBrain.getWorkBehaviors:()Ljava/util/List;
       228: invokeinterface #433,  2          // InterfaceMethod java/util/List.addAll:(Ljava/util/Collection;)Z
       233: pop
       234: goto          197
       237: aload_0
       238: getstatic     #436                // Field net/minecraft/world/entity/schedule/Activity.WORK:Lnet/minecraft/world/entity/schedule/Activity;
       241: aload         4
       243: invokestatic  #113                // Method com/google/common/collect/ImmutableList.copyOf:(Ljava/util/Collection;)Lcom/google/common/collect/ImmutableList;
       246: invokevirtual #328                // Method net/minecraft/world/entity/ai/Brain.addActivity:(Lnet/minecraft/world/entity/schedule/Activity;Lcom/google/common/collect/ImmutableList;)V
       249: return

  private static void registerRestGoals(net.minecraft.world.entity.ai.Brain<com.github.tartaricacid.touhoulittlemaid.entity.passive.EntityMaid>);
    Code:
         0: iconst_5
         1: invokestatic  #245                // Method java/lang/Integer.valueOf:(I)Ljava/lang/Integer;
         4: new           #443                // class com/github/tartaricacid/touhoulittlemaid/entity/ai/brain/task/MaidBedTask
         7: dup
         8: ldc_w         #313                // float 0.6f
        11: iconst_2
        12: invokespecial #444                // Method com/github/tartaricacid/touhoulittlemaid/entity/ai/brain/task/MaidBedTask."<init>":(FI)V
        15: invokestatic  #256                // Method com/mojang/datafixers/util/Pair.of:(Ljava/lang/Object;Ljava/lang/Object;)Lcom/mojang/datafixers/util/Pair;
        18: astore_1
        19: bipush        20
        21: invokestatic  #245                // Method java/lang/Integer.valueOf:(I)Ljava/lang/Integer;
        24: invokedynamic #449,  0            // InvokeDynamic #7:test:()Ljava/util/function/Predicate;
        29: invokestatic  #374                // Method getLookAndRandomWalk:(Ljava/util/function/Predicate;)Lcom/github/tartaricacid/touhoulittlemaid/entity/ai/brain/task/MaidRunOne;
        32: invokestatic  #256                // Method com/mojang/datafixers/util/Pair.of:(Ljava/lang/Object;Ljava/lang/Object;)Lcom/mojang/datafixers/util/Pair;
        35: astore_2
        36: bipush        99
        38: invokestatic  #245                // Method java/lang/Integer.valueOf:(I)Ljava/lang/Integer;
        41: new           #198                // class com/github/tartaricacid/touhoulittlemaid/entity/ai/brain/task/MaidUpdateActivityFromSchedule
        44: dup
        45: invokespecial #375                // Method com/github/tartaricacid/touhoulittlemaid/entity/ai/brain/task/MaidUpdateActivityFromSchedule."<init>":()V
        48: invokestatic  #256                // Method com/mojang/datafixers/util/Pair.of:(Ljava/lang/Object;Ljava/lang/Object;)Lcom/mojang/datafixers/util/Pair;
        51: astore_3
        52: iconst_3
        53: anewarray     #253                // class com/mojang/datafixers/util/Pair
        56: dup
        57: iconst_0
        58: aload_1
        59: aastore
        60: dup
        61: iconst_1
        62: aload_2
        63: aastore
        64: dup
        65: iconst_2
        66: aload_3
        67: aastore
        68: invokestatic  #75                 // Method com/google/common/collect/Lists.newArrayList:([Ljava/lang/Object;)Ljava/util/ArrayList;
        71: astore        4
        73: getstatic     #81                 // Field com/github/tartaricacid/touhoulittlemaid/entity/ai/brain/ExtraMaidBrainManager.EXTRA_MAID_BRAINS:Ljava/util/List;
        76: aload         4
        78: invokedynamic #454,  0            // InvokeDynamic #8:accept:(Ljava/util/List;)Ljava/util/function/Consumer;
        83: invokeinterface #107,  2          // InterfaceMethod java/util/List.forEach:(Ljava/util/function/Consumer;)V
        88: aload_0
        89: getstatic     #457                // Field net/minecraft/world/entity/schedule/Activity.REST:Lnet/minecraft/world/entity/schedule/Activity;
        92: aload         4
        94: invokestatic  #113                // Method com/google/common/collect/ImmutableList.copyOf:(Ljava/util/Collection;)Lcom/google/common/collect/ImmutableList;
        97: invokevirtual #328                // Method net/minecraft/world/entity/ai/Brain.addActivity:(Lnet/minecraft/world/entity/schedule/Activity;Lcom/google/common/collect/ImmutableList;)V
       100: return

  private static void registerPanicGoals(net.minecraft.world.entity.ai.Brain<com.github.tartaricacid.touhoulittlemaid.entity.passive.EntityMaid>);
    Code:
         0: iconst_5
         1: invokestatic  #245                // Method java/lang/Integer.valueOf:(I)Ljava/lang/Integer;
         4: new           #460                // class com/github/tartaricacid/touhoulittlemaid/entity/ai/brain/task/MaidClearHurtTask
         7: dup
         8: invokespecial #461                // Method com/github/tartaricacid/touhoulittlemaid/entity/ai/brain/task/MaidClearHurtTask."<init>":()V
        11: invokestatic  #256                // Method com/mojang/datafixers/util/Pair.of:(Ljava/lang/Object;Ljava/lang/Object;)Lcom/mojang/datafixers/util/Pair;
        14: astore_1
        15: iconst_5
        16: invokestatic  #245                // Method java/lang/Integer.valueOf:(I)Ljava/lang/Integer;
        19: getstatic     #36                 // Field net/minecraft/world/entity/ai/memory/MemoryModuleType.NEAREST_HOSTILE:Lnet/minecraft/world/entity/ai/memory/MemoryModuleType;
        22: ldc_w         #462                // float 0.7f
        25: iconst_0
        26: invokestatic  #468                // Method com/github/tartaricacid/touhoulittlemaid/entity/ai/brain/task/MaidRunAwayTask.entity:(Lnet/minecraft/world/entity/ai/memory/MemoryModuleType;FZ)Lcom/github/tartaricacid/touhoulittlemaid/entity/ai/brain/task/MaidRunAwayTask;
        29: invokestatic  #256                // Method com/mojang/datafixers/util/Pair.of:(Ljava/lang/Object;Ljava/lang/Object;)Lcom/mojang/datafixers/util/Pair;
        32: astore_2
        33: iconst_2
        34: anewarray     #253                // class com/mojang/datafixers/util/Pair
        37: dup
        38: iconst_0
        39: aload_1
        40: aastore
        41: dup
        42: iconst_1
        43: aload_2
        44: aastore
        45: invokestatic  #75                 // Method com/google/common/collect/Lists.newArrayList:([Ljava/lang/Object;)Ljava/util/ArrayList;
        48: astore_3
        49: getstatic     #81                 // Field com/github/tartaricacid/touhoulittlemaid/entity/ai/brain/ExtraMaidBrainManager.EXTRA_MAID_BRAINS:Ljava/util/List;
        52: aload_3
        53: invokedynamic #473,  0            // InvokeDynamic #9:accept:(Ljava/util/List;)Ljava/util/function/Consumer;
        58: invokeinterface #107,  2          // InterfaceMethod java/util/List.forEach:(Ljava/util/function/Consumer;)V
        63: aload_0
        64: getstatic     #476                // Field net/minecraft/world/entity/schedule/Activity.PANIC:Lnet/minecraft/world/entity/schedule/Activity;
        67: aload_3
        68: invokestatic  #113                // Method com/google/common/collect/ImmutableList.copyOf:(Ljava/util/Collection;)Lcom/google/common/collect/ImmutableList;
        71: invokevirtual #328                // Method net/minecraft/world/entity/ai/Brain.addActivity:(Lnet/minecraft/world/entity/schedule/Activity;Lcom/google/common/collect/ImmutableList;)V
        74: return

  private static void registerRideIdleGoals(net.minecraft.world.entity.ai.Brain<com.github.tartaricacid.touhoulittlemaid.entity.passive.EntityMaid>);
    Code:
         0: iconst_4
         1: invokestatic  #245                // Method java/lang/Integer.valueOf:(I)Ljava/lang/Integer;
         4: new           #480                // class com/github/tartaricacid/touhoulittlemaid/entity/ai/brain/ride/MaidRideBegTask
         7: dup
         8: invokespecial #481                // Method com/github/tartaricacid/touhoulittlemaid/entity/ai/brain/ride/MaidRideBegTask."<init>":()V
        11: invokestatic  #256                // Method com/mojang/datafixers/util/Pair.of:(Ljava/lang/Object;Ljava/lang/Object;)Lcom/mojang/datafixers/util/Pair;
        14: astore_1
        15: iconst_5
        16: invokestatic  #245                // Method java/lang/Integer.valueOf:(I)Ljava/lang/Integer;
        19: new           #483                // class com/github/tartaricacid/touhoulittlemaid/entity/ai/brain/task/MaidHomeMealTask
        22: dup
        23: invokespecial #484                // Method com/github/tartaricacid/touhoulittlemaid/entity/ai/brain/task/MaidHomeMealTask."<init>":()V
        26: invokestatic  #256                // Method com/mojang/datafixers/util/Pair.of:(Ljava/lang/Object;Ljava/lang/Object;)Lcom/mojang/datafixers/util/Pair;
        29: astore_2
        30: bipush        6
        32: invokestatic  #245                // Method java/lang/Integer.valueOf:(I)Ljava/lang/Integer;
        35: invokedynamic #489,  0            // InvokeDynamic #10:test:()Ljava/util/function/Predicate;
        40: invokestatic  #492                // Method getLook:(Ljava/util/function/Predicate;)Lcom/github/tartaricacid/touhoulittlemaid/entity/ai/brain/task/MaidRunOne;
        43: invokestatic  #256                // Method com/mojang/datafixers/util/Pair.of:(Ljava/lang/Object;Ljava/lang/Object;)Lcom/mojang/datafixers/util/Pair;
        46: astore_3
        47: bipush        99
        49: invokestatic  #245                // Method java/lang/Integer.valueOf:(I)Ljava/lang/Integer;
        52: new           #198                // class com/github/tartaricacid/touhoulittlemaid/entity/ai/brain/task/MaidUpdateActivityFromSchedule
        55: dup
        56: invokespecial #375                // Method com/github/tartaricacid/touhoulittlemaid/entity/ai/brain/task/MaidUpdateActivityFromSchedule."<init>":()V
        59: invokestatic  #256                // Method com/mojang/datafixers/util/Pair.of:(Ljava/lang/Object;Ljava/lang/Object;)Lcom/mojang/datafixers/util/Pair;
        62: astore        4
        64: iconst_4
        65: anewarray     #253                // class com/mojang/datafixers/util/Pair
        68: dup
        69: iconst_0
        70: aload_1
        71: aastore
        72: dup
        73: iconst_1
        74: aload_2
        75: aastore
        76: dup
        77: iconst_2
        78: aload_3
        79: aastore
        80: dup
        81: iconst_3
        82: aload         4
        84: aastore
        85: invokestatic  #75                 // Method com/google/common/collect/Lists.newArrayList:([Ljava/lang/Object;)Ljava/util/ArrayList;
        88: astore        5
        90: getstatic     #81                 // Field com/github/tartaricacid/touhoulittlemaid/entity/ai/brain/ExtraMaidBrainManager.EXTRA_MAID_BRAINS:Ljava/util/List;
        93: aload         5
        95: invokedynamic #497,  0            // InvokeDynamic #11:accept:(Ljava/util/List;)Ljava/util/function/Consumer;
       100: invokeinterface #107,  2          // InterfaceMethod java/util/List.forEach:(Ljava/util/function/Consumer;)V
       105: aload_0
       106: getstatic     #500                // Field com/github/tartaricacid/touhoulittlemaid/init/InitEntities.RIDE_IDLE:Ljava/util/function/Supplier;
       109: invokeinterface #66,  1           // InterfaceMethod java/util/function/Supplier.get:()Ljava/lang/Object;
       114: checkcast     #170                // class net/minecraft/world/entity/schedule/Activity
       117: aload         5
       119: invokestatic  #113                // Method com/google/common/collect/ImmutableList.copyOf:(Ljava/util/Collection;)Lcom/google/common/collect/ImmutableList;
       122: invokevirtual #328                // Method net/minecraft/world/entity/ai/Brain.addActivity:(Lnet/minecraft/world/entity/schedule/Activity;Lcom/google/common/collect/ImmutableList;)V
       125: return

  private static void registerRideWorkGoals(net.minecraft.world.entity.ai.Brain<com.github.tartaricacid.touhoulittlemaid.entity.passive.EntityMaid>, com.github.tartaricacid.touhoulittlemaid.entity.passive.EntityMaid);
    Code:
         0: bipush        99
         2: invokestatic  #245                // Method java/lang/Integer.valueOf:(I)Ljava/lang/Integer;
         5: new           #198                // class com/github/tartaricacid/touhoulittlemaid/entity/ai/brain/task/MaidUpdateActivityFromSchedule
         8: dup
         9: invokespecial #375                // Method com/github/tartaricacid/touhoulittlemaid/entity/ai/brain/task/MaidUpdateActivityFromSchedule."<init>":()V
        12: invokestatic  #256                // Method com/mojang/datafixers/util/Pair.of:(Ljava/lang/Object;Ljava/lang/Object;)Lcom/mojang/datafixers/util/Pair;
        15: astore_2
        16: aload_1
        17: invokevirtual #391                // Method com/github/tartaricacid/touhoulittlemaid/entity/passive/EntityMaid.getTask:()Lcom/github/tartaricacid/touhoulittlemaid/api/task/IMaidTask;
        20: astore_3
        21: aload_3
        22: aload_1
        23: invokeinterface #503,  2          // InterfaceMethod com/github/tartaricacid/touhoulittlemaid/api/task/IMaidTask.createRideBrainTasks:(Lcom/github/tartaricacid/touhoulittlemaid/entity/passive/EntityMaid;)Ljava/util/List;
        28: astore        4
        30: aload         4
        32: invokeinterface #400,  1          // InterfaceMethod java/util/List.isEmpty:()Z
        37: ifeq          56
        40: iconst_1
        41: anewarray     #253                // class com/mojang/datafixers/util/Pair
        44: dup
        45: iconst_0
        46: aload_2
        47: aastore
        48: invokestatic  #75                 // Method com/google/common/collect/Lists.newArrayList:([Ljava/lang/Object;)Ljava/util/ArrayList;
        51: astore        4
        53: goto          65
        56: aload         4
        58: aload_2
        59: invokeinterface #403,  2          // InterfaceMethod java/util/List.add:(Ljava/lang/Object;)Z
        64: pop
        65: aload         4
        67: bipush        6
        69: invokestatic  #245                // Method java/lang/Integer.valueOf:(I)Ljava/lang/Integer;
        72: new           #480                // class com/github/tartaricacid/touhoulittlemaid/entity/ai/brain/ride/MaidRideBegTask
        75: dup
        76: invokespecial #481                // Method com/github/tartaricacid/touhoulittlemaid/entity/ai/brain/ride/MaidRideBegTask."<init>":()V
        79: invokestatic  #256                // Method com/mojang/datafixers/util/Pair.of:(Ljava/lang/Object;Ljava/lang/Object;)Lcom/mojang/datafixers/util/Pair;
        82: invokeinterface #403,  2          // InterfaceMethod java/util/List.add:(Ljava/lang/Object;)Z
        87: pop
        88: aload         4
        90: bipush        7
        92: invokestatic  #245                // Method java/lang/Integer.valueOf:(I)Ljava/lang/Integer;
        95: new           #405                // class com/github/tartaricacid/touhoulittlemaid/entity/ai/brain/task/MaidWorkMealTask
        98: dup
        99: invokespecial #406                // Method com/github/tartaricacid/touhoulittlemaid/entity/ai/brain/task/MaidWorkMealTask."<init>":()V
       102: invokestatic  #256                // Method com/mojang/datafixers/util/Pair.of:(Ljava/lang/Object;Ljava/lang/Object;)Lcom/mojang/datafixers/util/Pair;
       105: invokeinterface #403,  2          // InterfaceMethod java/util/List.add:(Ljava/lang/Object;)Z
       110: pop
       111: aload         4
       113: bipush        20
       115: invokestatic  #245                // Method java/lang/Integer.valueOf:(I)Ljava/lang/Integer;
       118: invokedynamic #508,  0            // InvokeDynamic #12:test:()Ljava/util/function/Predicate;
       123: invokestatic  #492                // Method getLook:(Ljava/util/function/Predicate;)Lcom/github/tartaricacid/touhoulittlemaid/entity/ai/brain/task/MaidRunOne;
       126: invokestatic  #256                // Method com/mojang/datafixers/util/Pair.of:(Ljava/lang/Object;Ljava/lang/Object;)Lcom/mojang/datafixers/util/Pair;
       129: invokeinterface #403,  2          // InterfaceMethod java/util/List.add:(Ljava/lang/Object;)Z
       134: pop
       135: getstatic     #81                 // Field com/github/tartaricacid/touhoulittlemaid/entity/ai/brain/ExtraMaidBrainManager.EXTRA_MAID_BRAINS:Ljava/util/List;
       138: invokeinterface #415,  1          // InterfaceMethod java/util/List.iterator:()Ljava/util/Iterator;
       143: astore        5
       145: aload         5
       147: invokeinterface #420,  1          // InterfaceMethod java/util/Iterator.hasNext:()Z
       152: ifeq          185
       155: aload         5
       157: invokeinterface #423,  1          // InterfaceMethod java/util/Iterator.next:()Ljava/lang/Object;
       162: checkcast     #425                // class com/github/tartaricacid/touhoulittlemaid/api/entity/ai/IExtraMaidBrain
       165: astore        6
       167: aload         4
       169: aload         6
       171: invokeinterface #511,  1          // InterfaceMethod com/github/tartaricacid/touhoulittlemaid/api/entity/ai/IExtraMaidBrain.getRideWorkBehaviors:()Ljava/util/List;
       176: invokeinterface #433,  2          // InterfaceMethod java/util/List.addAll:(Ljava/util/Collection;)Z
       181: pop
       182: goto          145
       185: aload_0
       186: getstatic     #514                // Field com/github/tartaricacid/touhoulittlemaid/init/InitEntities.RIDE_WORK:Ljava/util/function/Supplier;
       189: invokeinterface #66,  1           // InterfaceMethod java/util/function/Supplier.get:()Ljava/lang/Object;
       194: checkcast     #170                // class net/minecraft/world/entity/schedule/Activity
       197: aload         4
       199: invokestatic  #113                // Method com/google/common/collect/ImmutableList.copyOf:(Ljava/util/Collection;)Lcom/google/common/collect/ImmutableList;
       202: invokevirtual #328                // Method net/minecraft/world/entity/ai/Brain.addActivity:(Lnet/minecraft/world/entity/schedule/Activity;Lcom/google/common/collect/ImmutableList;)V
       205: return

  private static void registerRideRestGoals(net.minecraft.world.entity.ai.Brain<com.github.tartaricacid.touhoulittlemaid.entity.passive.EntityMaid>);
    Code:
         0: bipush        99
         2: invokestatic  #245                // Method java/lang/Integer.valueOf:(I)Ljava/lang/Integer;
         5: new           #198                // class com/github/tartaricacid/touhoulittlemaid/entity/ai/brain/task/MaidUpdateActivityFromSchedule
         8: dup
         9: invokespecial #375                // Method com/github/tartaricacid/touhoulittlemaid/entity/ai/brain/task/MaidUpdateActivityFromSchedule."<init>":()V
        12: invokestatic  #256                // Method com/mojang/datafixers/util/Pair.of:(Ljava/lang/Object;Ljava/lang/Object;)Lcom/mojang/datafixers/util/Pair;
        15: astore_1
        16: iconst_1
        17: anewarray     #253                // class com/mojang/datafixers/util/Pair
        20: dup
        21: iconst_0
        22: aload_1
        23: aastore
        24: invokestatic  #75                 // Method com/google/common/collect/Lists.newArrayList:([Ljava/lang/Object;)Ljava/util/ArrayList;
        27: astore_2
        28: getstatic     #81                 // Field com/github/tartaricacid/touhoulittlemaid/entity/ai/brain/ExtraMaidBrainManager.EXTRA_MAID_BRAINS:Ljava/util/List;
        31: aload_2
        32: invokedynamic #519,  0            // InvokeDynamic #13:accept:(Ljava/util/List;)Ljava/util/function/Consumer;
        37: invokeinterface #107,  2          // InterfaceMethod java/util/List.forEach:(Ljava/util/function/Consumer;)V
        42: aload_0
        43: getstatic     #522                // Field com/github/tartaricacid/touhoulittlemaid/init/InitEntities.RIDE_REST:Ljava/util/function/Supplier;
        46: invokeinterface #66,  1           // InterfaceMethod java/util/function/Supplier.get:()Ljava/lang/Object;
        51: checkcast     #170                // class net/minecraft/world/entity/schedule/Activity
        54: aload_2
        55: invokestatic  #113                // Method com/google/common/collect/ImmutableList.copyOf:(Ljava/util/Collection;)Lcom/google/common/collect/ImmutableList;
        58: invokevirtual #328                // Method net/minecraft/world/entity/ai/Brain.addActivity:(Lnet/minecraft/world/entity/schedule/Activity;Lcom/google/common/collect/ImmutableList;)V
        61: return

  private static com.github.tartaricacid.touhoulittlemaid.entity.ai.brain.task.MaidRunOne getLookAndRandomWalk(java.util.function.Predicate<com.github.tartaricacid.touhoulittlemaid.entity.passive.EntityMaid>);
    Code:
         0: getstatic     #529                // Field net/minecraft/world/entity/EntityType.PLAYER:Lnet/minecraft/world/entity/EntityType;
         3: ldc_w         #530                // float 5.0f
         6: invokestatic  #535                // Method net/minecraft/world/entity/ai/behavior/SetEntityLookTarget.create:(Lnet/minecraft/world/entity/EntityType;F)Lnet/minecraft/world/entity/ai/behavior/OneShot;
         9: iconst_1
        10: invokestatic  #245                // Method java/lang/Integer.valueOf:(I)Ljava/lang/Integer;
        13: invokestatic  #256                // Method com/mojang/datafixers/util/Pair.of:(Ljava/lang/Object;Ljava/lang/Object;)Lcom/mojang/datafixers/util/Pair;
        16: astore_1
        17: getstatic     #538                // Field com/github/tartaricacid/touhoulittlemaid/entity/passive/EntityMaid.TYPE:Lnet/minecraft/world/entity/EntityType;
        20: ldc_w         #530                // float 5.0f
        23: invokestatic  #535                // Method net/minecraft/world/entity/ai/behavior/SetEntityLookTarget.create:(Lnet/minecraft/world/entity/EntityType;F)Lnet/minecraft/world/entity/ai/behavior/OneShot;
        26: iconst_1
        27: invokestatic  #245                // Method java/lang/Integer.valueOf:(I)Ljava/lang/Integer;
        30: invokestatic  #256                // Method com/mojang/datafixers/util/Pair.of:(Ljava/lang/Object;Ljava/lang/Object;)Lcom/mojang/datafixers/util/Pair;
        33: astore_2
        34: getstatic     #541                // Field net/minecraft/world/entity/EntityType.WOLF:Lnet/minecraft/world/entity/EntityType;
        37: ldc_w         #530                // float 5.0f
        40: invokestatic  #535                // Method net/minecraft/world/entity/ai/behavior/SetEntityLookTarget.create:(Lnet/minecraft/world/entity/EntityType;F)Lnet/minecraft/world/entity/ai/behavior/OneShot;
        43: iconst_1
        44: invokestatic  #245                // Method java/lang/Integer.valueOf:(I)Ljava/lang/Integer;
        47: invokestatic  #256                // Method com/mojang/datafixers/util/Pair.of:(Ljava/lang/Object;Ljava/lang/Object;)Lcom/mojang/datafixers/util/Pair;
        50: astore_3
        51: getstatic     #544                // Field net/minecraft/world/entity/EntityType.CAT:Lnet/minecraft/world/entity/EntityType;
        54: ldc_w         #530                // float 5.0f
        57: invokestatic  #535                // Method net/minecraft/world/entity/ai/behavior/SetEntityLookTarget.create:(Lnet/minecraft/world/entity/EntityType;F)Lnet/minecraft/world/entity/ai/behavior/OneShot;
        60: iconst_1
        61: invokestatic  #245                // Method java/lang/Integer.valueOf:(I)Ljava/lang/Integer;
        64: invokestatic  #256                // Method com/mojang/datafixers/util/Pair.of:(Ljava/lang/Object;Ljava/lang/Object;)Lcom/mojang/datafixers/util/Pair;
        67: astore        4
        69: getstatic     #547                // Field net/minecraft/world/entity/EntityType.PARROT:Lnet/minecraft/world/entity/EntityType;
        72: ldc_w         #530                // float 5.0f
        75: invokestatic  #535                // Method net/minecraft/world/entity/ai/behavior/SetEntityLookTarget.create:(Lnet/minecraft/world/entity/EntityType;F)Lnet/minecraft/world/entity/ai/behavior/OneShot;
        78: iconst_1
        79: invokestatic  #245                // Method java/lang/Integer.valueOf:(I)Ljava/lang/Integer;
        82: invokestatic  #256                // Method com/mojang/datafixers/util/Pair.of:(Ljava/lang/Object;Ljava/lang/Object;)Lcom/mojang/datafixers/util/Pair;
        85: astore        5
        87: ldc_w         #548                // float 0.3f
        90: iconst_5
        91: iconst_3
        92: invokestatic  #554                // Method net/minecraft/world/entity/ai/behavior/RandomStroll.stroll:(FII)Lnet/minecraft/world/entity/ai/behavior/BehaviorControl;
        95: iconst_1
        96: invokestatic  #245                // Method java/lang/Integer.valueOf:(I)Ljava/lang/Integer;
        99: invokestatic  #256                // Method com/mojang/datafixers/util/Pair.of:(Ljava/lang/Object;Ljava/lang/Object;)Lcom/mojang/datafixers/util/Pair;
       102: astore        6
       104: new           #556                // class net/minecraft/world/entity/ai/behavior/DoNothing
       107: dup
       108: bipush        30
       110: bipush        60
       112: invokespecial #557                // Method net/minecraft/world/entity/ai/behavior/DoNothing."<init>":(II)V
       115: iconst_2
       116: invokestatic  #245                // Method java/lang/Integer.valueOf:(I)Ljava/lang/Integer;
       119: invokestatic  #256                // Method com/mojang/datafixers/util/Pair.of:(Ljava/lang/Object;Ljava/lang/Object;)Lcom/mojang/datafixers/util/Pair;
       122: astore        7
       124: new           #559                // class com/github/tartaricacid/touhoulittlemaid/entity/ai/brain/task/MaidRunOne
       127: dup
       128: aload_1
       129: aload_2
       130: aload_3
       131: aload         4
       133: aload         5
       135: aload         6
       137: aload         7
       139: invokestatic  #562                // Method com/google/common/collect/ImmutableList.of:(Ljava/lang/Object;Ljava/lang/Object;Ljava/lang/Object;Ljava/lang/Object;Ljava/lang/Object;Ljava/lang/Object;Ljava/lang/Object;)Lcom/google/common/collect/ImmutableList;
       142: aload_0
       143: invokespecial #565                // Method com/github/tartaricacid/touhoulittlemaid/entity/ai/brain/task/MaidRunOne."<init>":(Ljava/util/List;Ljava/util/function/Predicate;)V
       146: areturn

  private static com.github.tartaricacid.touhoulittlemaid.entity.ai.brain.task.MaidRunOne getLook(java.util.function.Predicate<com.github.tartaricacid.touhoulittlemaid.entity.passive.EntityMaid>);
    Code:
         0: getstatic     #529                // Field net/minecraft/world/entity/EntityType.PLAYER:Lnet/minecraft/world/entity/EntityType;
         3: ldc_w         #530                // float 5.0f
         6: invokestatic  #535                // Method net/minecraft/world/entity/ai/behavior/SetEntityLookTarget.create:(Lnet/minecraft/world/entity/EntityType;F)Lnet/minecraft/world/entity/ai/behavior/OneShot;
         9: iconst_1
        10: invokestatic  #245                // Method java/lang/Integer.valueOf:(I)Ljava/lang/Integer;
        13: invokestatic  #256                // Method com/mojang/datafixers/util/Pair.of:(Ljava/lang/Object;Ljava/lang/Object;)Lcom/mojang/datafixers/util/Pair;
        16: astore_1
        17: getstatic     #538                // Field com/github/tartaricacid/touhoulittlemaid/entity/passive/EntityMaid.TYPE:Lnet/minecraft/world/entity/EntityType;
        20: ldc_w         #530                // float 5.0f
        23: invokestatic  #535                // Method net/minecraft/world/entity/ai/behavior/SetEntityLookTarget.create:(Lnet/minecraft/world/entity/EntityType;F)Lnet/minecraft/world/entity/ai/behavior/OneShot;
        26: iconst_1
        27: invokestatic  #245                // Method java/lang/Integer.valueOf:(I)Ljava/lang/Integer;
        30: invokestatic  #256                // Method com/mojang/datafixers/util/Pair.of:(Ljava/lang/Object;Ljava/lang/Object;)Lcom/mojang/datafixers/util/Pair;
        33: astore_2
        34: getstatic     #541                // Field net/minecraft/world/entity/EntityType.WOLF:Lnet/minecraft/world/entity/EntityType;
        37: ldc_w         #530                // float 5.0f
        40: invokestatic  #535                // Method net/minecraft/world/entity/ai/behavior/SetEntityLookTarget.create:(Lnet/minecraft/world/entity/EntityType;F)Lnet/minecraft/world/entity/ai/behavior/OneShot;
        43: iconst_1
        44: invokestatic  #245                // Method java/lang/Integer.valueOf:(I)Ljava/lang/Integer;
        47: invokestatic  #256                // Method com/mojang/datafixers/util/Pair.of:(Ljava/lang/Object;Ljava/lang/Object;)Lcom/mojang/datafixers/util/Pair;
        50: astore_3
        51: getstatic     #544                // Field net/minecraft/world/entity/EntityType.CAT:Lnet/minecraft/world/entity/EntityType;
        54: ldc_w         #530                // float 5.0f
        57: invokestatic  #535                // Method net/minecraft/world/entity/ai/behavior/SetEntityLookTarget.create:(Lnet/minecraft/world/entity/EntityType;F)Lnet/minecraft/world/entity/ai/behavior/OneShot;
        60: iconst_1
        61: invokestatic  #245                // Method java/lang/Integer.valueOf:(I)Ljava/lang/Integer;
        64: invokestatic  #256                // Method com/mojang/datafixers/util/Pair.of:(Ljava/lang/Object;Ljava/lang/Object;)Lcom/mojang/datafixers/util/Pair;
        67: astore        4
        69: getstatic     #547                // Field net/minecraft/world/entity/EntityType.PARROT:Lnet/minecraft/world/entity/EntityType;
        72: ldc_w         #530                // float 5.0f
        75: invokestatic  #535                // Method net/minecraft/world/entity/ai/behavior/SetEntityLookTarget.create:(Lnet/minecraft/world/entity/EntityType;F)Lnet/minecraft/world/entity/ai/behavior/OneShot;
        78: iconst_1
        79: invokestatic  #245                // Method java/lang/Integer.valueOf:(I)Ljava/lang/Integer;
        82: invokestatic  #256                // Method com/mojang/datafixers/util/Pair.of:(Ljava/lang/Object;Ljava/lang/Object;)Lcom/mojang/datafixers/util/Pair;
        85: astore        5
        87: new           #556                // class net/minecraft/world/entity/ai/behavior/DoNothing
        90: dup
        91: bipush        30
        93: bipush        60
        95: invokespecial #557                // Method net/minecraft/world/entity/ai/behavior/DoNothing."<init>":(II)V
        98: iconst_2
        99: invokestatic  #245                // Method java/lang/Integer.valueOf:(I)Ljava/lang/Integer;
       102: invokestatic  #256                // Method com/mojang/datafixers/util/Pair.of:(Ljava/lang/Object;Ljava/lang/Object;)Lcom/mojang/datafixers/util/Pair;
       105: astore        6
       107: new           #559                // class com/github/tartaricacid/touhoulittlemaid/entity/ai/brain/task/MaidRunOne
       110: dup
       111: aload_1
       112: aload_2
       113: aload_3
       114: aload         4
       116: aload         5
       118: aload         6
       120: invokestatic  #579                // Method com/google/common/collect/ImmutableList.of:(Ljava/lang/Object;Ljava/lang/Object;Ljava/lang/Object;Ljava/lang/Object;Ljava/lang/Object;Ljava/lang/Object;)Lcom/google/common/collect/ImmutableList;
       123: aload_0
       124: invokespecial #565                // Method com/github/tartaricacid/touhoulittlemaid/entity/ai/brain/task/MaidRunOne."<init>":(Ljava/util/List;Ljava/util/function/Predicate;)V
       127: areturn

  private static void lambda$registerRideRestGoals$12(java.util.List, com.github.tartaricacid.touhoulittlemaid.api.entity.ai.IExtraMaidBrain);
    Code:
         0: aload_0
         1: aload_1
         2: invokeinterface #582,  1          // InterfaceMethod com/github/tartaricacid/touhoulittlemaid/api/entity/ai/IExtraMaidBrain.getRideRestBehaviors:()Ljava/util/List;
         7: invokeinterface #433,  2          // InterfaceMethod java/util/List.addAll:(Ljava/util/Collection;)Z
        12: pop
        13: return

  private static boolean lambda$registerRideWorkGoals$11(com.github.tartaricacid.touhoulittlemaid.entity.passive.EntityMaid);
    Code:
         0: aload_0
         1: invokevirtual #391                // Method com/github/tartaricacid/touhoulittlemaid/entity/passive/EntityMaid.getTask:()Lcom/github/tartaricacid/touhoulittlemaid/api/task/IMaidTask;
         4: aload_0
         5: invokeinterface #585,  2          // InterfaceMethod com/github/tartaricacid/touhoulittlemaid/api/task/IMaidTask.enableLookAndRandomWalk:(Lcom/github/tartaricacid/touhoulittlemaid/entity/passive/EntityMaid;)Z
        10: ireturn

  private static void lambda$registerRideIdleGoals$10(java.util.List, com.github.tartaricacid.touhoulittlemaid.api.entity.ai.IExtraMaidBrain);
    Code:
         0: aload_0
         1: aload_1
         2: invokeinterface #589,  1          // InterfaceMethod com/github/tartaricacid/touhoulittlemaid/api/entity/ai/IExtraMaidBrain.getRideIdleBehaviors:()Ljava/util/List;
         7: invokeinterface #433,  2          // InterfaceMethod java/util/List.addAll:(Ljava/util/Collection;)Z
        12: pop
        13: return

  private static boolean lambda$registerRideIdleGoals$9(com.github.tartaricacid.touhoulittlemaid.entity.passive.EntityMaid);
    Code:
         0: iconst_1
         1: ireturn

  private static void lambda$registerPanicGoals$8(java.util.List, com.github.tartaricacid.touhoulittlemaid.api.entity.ai.IExtraMaidBrain);
    Code:
         0: aload_0
         1: aload_1
         2: invokeinterface #592,  1          // InterfaceMethod com/github/tartaricacid/touhoulittlemaid/api/entity/ai/IExtraMaidBrain.getPanicBehaviors:()Ljava/util/List;
         7: invokeinterface #433,  2          // InterfaceMethod java/util/List.addAll:(Ljava/util/Collection;)Z
        12: pop
        13: return

  private static void lambda$registerRestGoals$7(java.util.List, com.github.tartaricacid.touhoulittlemaid.api.entity.ai.IExtraMaidBrain);
    Code:
         0: aload_0
         1: aload_1
         2: invokeinterface #595,  1          // InterfaceMethod com/github/tartaricacid/touhoulittlemaid/api/entity/ai/IExtraMaidBrain.getRestBehaviors:()Ljava/util/List;
         7: invokeinterface #433,  2          // InterfaceMethod java/util/List.addAll:(Ljava/util/Collection;)Z
        12: pop
        13: return

  private static boolean lambda$registerRestGoals$6(com.github.tartaricacid.touhoulittlemaid.entity.passive.EntityMaid);
    Code:
         0: iconst_1
         1: ireturn

  private static boolean lambda$registerWorkGoals$5(com.github.tartaricacid.touhoulittlemaid.entity.passive.EntityMaid);
    Code:
         0: aload_0
         1: invokevirtual #391                // Method com/github/tartaricacid/touhoulittlemaid/entity/passive/EntityMaid.getTask:()Lcom/github/tartaricacid/touhoulittlemaid/api/task/IMaidTask;
         4: aload_0
         5: invokeinterface #585,  2          // InterfaceMethod com/github/tartaricacid/touhoulittlemaid/api/task/IMaidTask.enableLookAndRandomWalk:(Lcom/github/tartaricacid/touhoulittlemaid/entity/passive/EntityMaid;)Z
        10: ifeq          27
        13: aload_0
        14: invokevirtual #599                // Method com/github/tartaricacid/touhoulittlemaid/entity/passive/EntityMaid.getSwimManager:()Lcom/github/tartaricacid/touhoulittlemaid/entity/passive/MaidSwimManager;
        17: invokevirtual #604                // Method com/github/tartaricacid/touhoulittlemaid/entity/passive/MaidSwimManager.isGoingToBreath:()Z
        20: ifne          27
        23: iconst_1
        24: goto          28
        27: iconst_0
        28: ireturn

  private static void lambda$registerIdleGoals$4(java.util.List, com.github.tartaricacid.touhoulittlemaid.api.entity.ai.IExtraMaidBrain);
    Code:
         0: aload_0
         1: aload_1
         2: invokeinterface #607,  1          // InterfaceMethod com/github/tartaricacid/touhoulittlemaid/api/entity/ai/IExtraMaidBrain.getIdleBehaviors:()Ljava/util/List;
         7: invokeinterface #433,  2          // InterfaceMethod java/util/List.addAll:(Ljava/util/Collection;)Z
        12: pop
        13: return

  private static boolean lambda$registerIdleGoals$3(com.github.tartaricacid.touhoulittlemaid.entity.passive.EntityMaid);
    Code:
         0: aload_0
         1: invokevirtual #599                // Method com/github/tartaricacid/touhoulittlemaid/entity/passive/EntityMaid.getSwimManager:()Lcom/github/tartaricacid/touhoulittlemaid/entity/passive/MaidSwimManager;
         4: invokevirtual #604                // Method com/github/tartaricacid/touhoulittlemaid/entity/passive/MaidSwimManager.isGoingToBreath:()Z
         7: ifne          14
        10: iconst_1
        11: goto          15
        14: iconst_0
        15: ireturn

  private static void lambda$registerCoreGoals$2(java.util.List, com.github.tartaricacid.touhoulittlemaid.api.entity.ai.IExtraMaidBrain);
    Code:
         0: aload_0
         1: aload_1
         2: invokeinterface #610,  1          // InterfaceMethod com/github/tartaricacid/touhoulittlemaid/api/entity/ai/IExtraMaidBrain.getCoreBehaviors:()Ljava/util/List;
         7: invokeinterface #433,  2          // InterfaceMethod java/util/List.addAll:(Ljava/util/Collection;)Z
        12: pop
        13: return

  private static void lambda$getSensorTypes$1(java.util.List, com.github.tartaricacid.touhoulittlemaid.api.entity.ai.IExtraMaidBrain);
    Code:
         0: aload_0
         1: aload_1
         2: invokeinterface #613,  1          // InterfaceMethod com/github/tartaricacid/touhoulittlemaid/api/entity/ai/IExtraMaidBrain.getExtraSensorTypes:()Ljava/util/List;
         7: invokeinterface #433,  2          // InterfaceMethod java/util/List.addAll:(Ljava/util/Collection;)Z
        12: pop
        13: return

  private static void lambda$getMemoryTypes$0(java.util.List, com.github.tartaricacid.touhoulittlemaid.api.entity.ai.IExtraMaidBrain);
    Code:
         0: aload_0
         1: aload_1
         2: invokeinterface #616,  1          // InterfaceMethod com/github/tartaricacid/touhoulittlemaid/api/entity/ai/IExtraMaidBrain.getExtraMemoryTypes:()Ljava/util/List;
         7: invokeinterface #433,  2          // InterfaceMethod java/util/List.addAll:(Ljava/util/Collection;)Z
        12: pop
        13: return
}
